mlopsnotes/__init__.py
mlopsnotes/_modidx.py
mlopsnotes/core.py
mlopsnotes-0.0.1.dist-info/LICENSE
mlopsnotes-0.0.1.dist-info/METADATA
mlopsnotes-0.0.1.dist-info/WHEEL
mlopsnotes-0.0.1.dist-info/entry_points.txt
mlopsnotes-0.0.1.dist-info/top_level.txt
mlopsnotes-0.0.1.dist-info/RECORD
